{
  "urlInspection": [
    {
      "url": "https://oceancloudconsults.com/articles/guide-copilot-cowork-multi-team-workflows",
      "status": 200,
      "verdict": "NEUTRAL",
      "coverageState": "URL is unknown to Google",
      "robotsTxtState": "ROBOTS_TXT_STATE_UNSPECIFIED",
      "indexingState": "INDEXING_STATE_UNSPECIFIED",
      "pageFetchState": "PAGE_FETCH_STATE_UNSPECIFIED"
    },
    {
      "url": "https://oceancloudconsults.com/articles/guide-scout-adoption-governance",
      "status": 200,
      "verdict": "NEUTRAL",
      "coverageState": "URL is unknown to Google",
      "robotsTxtState": "ROBOTS_TXT_STATE_UNSPECIFIED",
      "indexingState": "INDEXING_STATE_UNSPECIFIED",
      "pageFetchState": "PAGE_FETCH_STATE_UNSPECIFIED"
    },
    {
      "url": "https://oceancloudconsults.com/articles/guide-work-iq-apis-organization-insights",
      "status": 200,
      "verdict": "NEUTRAL",
      "coverageState": "URL is unknown to Google",
      "robotsTxtState": "ROBOTS_TXT_STATE_UNSPECIFIED",
      "indexingState": "INDEXING_STATE_UNSPECIFIED",
      "pageFetchState": "PAGE_FETCH_STATE_UNSPECIFIED"
    },
    {
      "url": "https://oceancloudconsults.com/articles/guide-teams-phone-agents-custom-voice",
      "status": 200,
      "verdict": "NEUTRAL",
      "coverageState": "URL is unknown to Google",
      "robotsTxtState": "ROBOTS_TXT_STATE_UNSPECIFIED",
      "indexingState": "INDEXING_STATE_UNSPECIFIED",
      "pageFetchState": "PAGE_FETCH_STATE_UNSPECIFIED"
    },
    {
      "url": "https://oceancloudconsults.com/articles/guide-computer-using-agents-rpa-automation",
      "status": 200,
      "verdict": "NEUTRAL",
      "coverageState": "URL is unknown to Google",
      "robotsTxtState": "ROBOTS_TXT_STATE_UNSPECIFIED",
      "indexingState": "INDEXING_STATE_UNSPECIFIED",
      "pageFetchState": "PAGE_FETCH_STATE_UNSPECIFIED"
    }
  ]
}